notify_africa/__init__.py
notify_africa/client.py
notify_africa/exceptions.py
notify_africa/models.py
notify_africa/utils.py
notify_africa_sms-2.0.0.dist-info/licenses/LICENSE
tests/__init__.py
tests/test_client.py
tests/test_utils.py
notify_africa_sms-2.0.0.dist-info/METADATA
notify_africa_sms-2.0.0.dist-info/WHEEL
notify_africa_sms-2.0.0.dist-info/top_level.txt
notify_africa_sms-2.0.0.dist-info/RECORD
