Metadata-Version: 2.4
Name: notify-africa-sms
Version: 2.0.0
Summary: Python SDK for Notify Africa SMS API
Home-page: https://github.com/Godie360/Notify-Africa-Python-SDK
Author: Godfrey Enosh
Author-email: godfreyenos360@gmail.com
Classifier: Programming Language :: Python :: 3
Classifier: License :: OSI Approved :: MIT License
Classifier: Operating System :: OS Independent
Requires-Python: >=3.6
License-File: LICENSE
Requires-Dist: requests>=2.25.0
Requires-Dist: pandas>=1.3.0
Requires-Dist: openpyxl>=3.0.7
Requires-Dist: python-dateutil>=2.8.0
Dynamic: author
Dynamic: author-email
Dynamic: classifier
Dynamic: description
Dynamic: description-content-type
Dynamic: home-page
Dynamic: license-file
Dynamic: requires-dist
Dynamic: requires-python
Dynamic: summary
